membase_mcp/__init__.py
membase_mcp/server.py
mseep_membase_mcp-0.1.4.dist-info/METADATA
mseep_membase_mcp-0.1.4.dist-info/WHEEL
mseep_membase_mcp-0.1.4.dist-info/top_level.txt
mseep_membase_mcp-0.1.4.dist-info/RECORD
