Metadata-Version: 2.4
Name: mseep-membase-mcp
Version: 0.1.4
Summary: Add your description here
Author-email: mseep <support@skydeck.ai>
Requires-Python: >=3.10
Requires-Dist: mcp>=1.6.0
Requires-Dist: membase>=0.1.8
